{
    "type": "object",
    "properties": {
        "Action": {
            "required": true,
            "type": "string"
        },
        "Version": {
            "required": true,
            "type": "string"
        },
        "requestBody": {
            "description": "Represents the input of a <code>PurchaseReservedCacheNodesOffering</code> operation.",
            "properties": {
                "CacheNodeCount": {
                    "description": "<p>The number of cache node instances to reserve.</p> <p>Default: <code>1</code> </p>",
                    "type": "integer"
                },
                "ReservedCacheNodeId": {
                    "description": "<p>A customer-specified identifier to track this reservation.</p> <note> <p>The Reserved Cache Node ID is an unique customer-specified identifier to track this reservation. If this parameter is not specified, ElastiCache automatically generates an identifier for the reservation.</p> </note> <p>Example: myreservationID</p>",
                    "type": "string"
                },
                "ReservedCacheNodesOfferingId": {
                    "description": "<p>The ID of the reserved cache node offering to purchase.</p> <p>Example: <code>438012d3-4052-4cc7-b2e3-8d3372e0e706</code> </p>",
                    "type": "string"
                }
            },
            "required": [
                "ReservedCacheNodesOfferingId"
            ],
            "type": "object"
        },
        "X_Amz_Content_Sha256": {
            "required": false,
            "type": "string"
        },
        "X_Amz_Date": {
            "required": false,
            "type": "string"
        },
        "X_Amz_Algorithm": {
            "required": false,
            "type": "string"
        },
        "X_Amz_Credential": {
            "required": false,
            "type": "string"
        },
        "X_Amz_Security_Token": {
            "required": false,
            "type": "string"
        },
        "X_Amz_Signature": {
            "required": false,
            "type": "string"
        },
        "X_Amz_SignedHeaders": {
            "required": false,
            "type": "string"
        }
    }
}